[
    {
        "points": [
            [
                1074,
                400
            ],
            [
                1211,
                444
            ],
            [
                1211,
                636
            ],
            [
                1050,
                637
            ]
        ],
        "type": 0
    },
    {
        "points": [
            [
                899,
                340
            ],
            [
                1068,
                396
            ],
            [
                1037,
                634
            ],
            [
                794,
                508
            ]
        ],
        "type": 1
    },
    {
        "points": [
            [
                790,
                499
            ],
            [
                649,
                411
            ],
            [
                780,
                289
            ],
            [
                894,
                337
            ]
        ],
        "type": 1
    },
    {
        "points": [
            [
                646,
                406
            ],
            [
                776,
                287
            ],
            [
                701,
                248
            ],
            [
                575,
                337
            ]
        ],
        "type": 1
    },
    {
        "points": [
            [
                570,
                336
            ],
            [
                696,
                246
            ],
            [
                618,
                209
            ],
            [
                520,
                287
            ]
        ],
        "type": 0
    },
    {
        "points": [
            [
                514,
                292
            ],
            [
                475,
                257
            ],
            [
                552,
                193
            ],
            [
                615,
                206
            ]
        ],
        "type": 0
    },
    {
        "points": [
            [
                98,
                479
            ],
            [
                112,
                616
            ],
            [
                344,
                570
            ],
            [
                292,
                436
            ]
        ],
        "type": 0
    },
    {
        "points": [
            [
                81,
                289
            ],
            [
                200,
                272
            ],
            [
                162,
                218
            ],
            [
                75,
                227
            ]
        ],
        "type": 0
    },
    {
        "points": [
            [
                80,
                334
            ],
            [
                223,
                310
            ],
            [
                288,
                431
            ],
            [
                99,
                472
            ]
        ],
        "type": 0
    },
    {
        "points": [
            [
                291,
                190
            ],
            [
                370,
                152
            ],
            [
                328,
                142
            ],
            [
                263,
                166
            ]
        ],
        "type": 1
    },
    {
        "points": [
            [
                434,
                250
            ],
            [
                393,
                226
            ],
            [
                474,
                194
            ],
            [
                509,
                208
            ]
        ],
        "type": 0
    }
]